{
   "cif_okay": true,
   "problematic": false,
   "has_oms": true,
   "metal_sites": [
      {
         "metal": "Si",
         "type": "Closed",
         "is_open": false,
         "unique": true,
         "problematic": false,
         "number_of_linkers": 4,
         "t_factor": 0.9990499667119213
      },
      {
         "metal": "Si",
         "type": "Closed",
         "is_open": false,
         "unique": false,
         "problematic": false,
         "number_of_linkers": 4,
         "t_factor": 0.9990499667119217
      },
      {
         "metal": "Si",
         "type": "Closed",
         "is_open": false,
         "unique": false,
         "problematic": false,
         "number_of_linkers": 4,
         "t_factor": 0.9990499667119217
      },
      {
         "metal": "Si",
         "type": "Closed",
         "is_open": false,
         "unique": false,
         "problematic": false,
         "number_of_linkers": 4,
         "t_factor": 0.9990499667119213
      },
      {
         "metal": "Si",
         "type": "Closed",
         "is_open": false,
         "unique": false,
         "problematic": false,
         "number_of_linkers": 4,
         "t_factor": 0.9990499667119217
      },
      {
         "metal": "Si",
         "type": "Closed",
         "is_open": false,
         "unique": false,
         "problematic": false,
         "number_of_linkers": 4,
         "t_factor": 0.999049966711922
      },
      {
         "metal": "Si",
         "type": "Closed",
         "is_open": false,
         "unique": false,
         "problematic": false,
         "number_of_linkers": 4,
         "t_factor": 0.9990499667119213
      },
      {
         "metal": "Si",
         "type": "Closed",
         "is_open": false,
         "unique": false,
         "problematic": false,
         "number_of_linkers": 4,
         "t_factor": 0.9990499667119213
      },
      {
         "metal": "Si",
         "type": "Closed",
         "is_open": false,
         "unique": false,
         "problematic": false,
         "number_of_linkers": 4,
         "t_factor": 0.9990499667119218
      },
      {
         "metal": "Si",
         "type": "Closed",
         "is_open": false,
         "unique": false,
         "problematic": false,
         "number_of_linkers": 4,
         "t_factor": 0.9990499667119213
      },
      {
         "metal": "Si",
         "type": "Closed",
         "is_open": false,
         "unique": false,
         "problematic": false,
         "number_of_linkers": 4,
         "t_factor": 0.9990499667119213
      },
      {
         "metal": "Si",
         "type": "Closed",
         "is_open": false,
         "unique": false,
         "problematic": false,
         "number_of_linkers": 4,
         "t_factor": 0.9990499667119217
      },
      {
         "metal": "Si",
         "type": "Closed",
         "is_open": false,
         "unique": true,
         "problematic": false,
         "number_of_linkers": 4,
         "t_factor": 0.9982254668325217
      },
      {
         "metal": "Si",
         "type": "Closed",
         "is_open": false,
         "unique": false,
         "problematic": false,
         "number_of_linkers": 4,
         "t_factor": 0.998225466832521
      },
      {
         "metal": "Si",
         "type": "Closed",
         "is_open": false,
         "unique": false,
         "problematic": false,
         "number_of_linkers": 4,
         "t_factor": 0.9982254668325202
      },
      {
         "metal": "Si",
         "type": "Closed",
         "is_open": false,
         "unique": false,
         "problematic": false,
         "number_of_linkers": 4,
         "t_factor": 0.9982254668325212
      },
      {
         "metal": "Si",
         "type": "Closed",
         "is_open": false,
         "unique": false,
         "problematic": false,
         "number_of_linkers": 4,
         "t_factor": 0.9982254668325207
      },
      {
         "metal": "Si",
         "type": "Closed",
         "is_open": false,
         "unique": false,
         "problematic": false,
         "number_of_linkers": 4,
         "t_factor": 0.9982254668325219
      },
      {
         "metal": "Si",
         "type": "3_or_less",
         "is_open": true,
         "unique": true,
         "problematic": false,
         "number_of_linkers": 3,
         "t_factor": -1
      },
      {
         "metal": "Si",
         "type": "3_or_less",
         "is_open": true,
         "unique": false,
         "problematic": false,
         "number_of_linkers": 3,
         "t_factor": -1
      }
   ],
   "oms_density": 0.002483099085662802,
   "checksum": "eedf1b39b4bdcf1904671ee83e2321cf6fc4b9dd065f50e331a1dcd89062f632",
   "metal_species": [
      "Si"
   ],
   "non_metal_species": [
      "O"
   ],
   "name": "-WEN",
   "uc_volume": 1208.1676552183274,
   "density": 1.629640482047446,
   "date_created": "2022-03-08T13:13:17.599926"
}