{
   "cif_okay": true,
   "problematic": false,
   "has_oms": false,
   "metal_sites": [
      {
         "metal": "Si",
         "type": "Closed",
         "is_open": false,
         "unique": true,
         "problematic": false,
         "number_of_linkers": 4,
         "t_factor": 0.9966170593445652
      },
      {
         "metal": "Si",
         "type": "Closed",
         "is_open": false,
         "unique": false,
         "problematic": false,
         "number_of_linkers": 4,
         "t_factor": 0.996617059344565
      },
      {
         "metal": "Si",
         "type": "Closed",
         "is_open": false,
         "unique": false,
         "problematic": false,
         "number_of_linkers": 4,
         "t_factor": 0.996617059344565
      },
      {
         "metal": "Si",
         "type": "Closed",
         "is_open": false,
         "unique": false,
         "problematic": false,
         "number_of_linkers": 4,
         "t_factor": 0.9966170593445652
      },
      {
         "metal": "Si",
         "type": "Closed",
         "is_open": false,
         "unique": false,
         "problematic": false,
         "number_of_linkers": 4,
         "t_factor": 0.996617059344565
      },
      {
         "metal": "Si",
         "type": "Closed",
         "is_open": false,
         "unique": false,
         "problematic": false,
         "number_of_linkers": 4,
         "t_factor": 0.996617059344565
      },
      {
         "metal": "Si",
         "type": "Closed",
         "is_open": false,
         "unique": false,
         "problematic": false,
         "number_of_linkers": 4,
         "t_factor": 0.9966170593445652
      },
      {
         "metal": "Si",
         "type": "Closed",
         "is_open": false,
         "unique": false,
         "problematic": false,
         "number_of_linkers": 4,
         "t_factor": 0.9966170593445652
      }
   ],
   "oms_density": 0.0022140945057761,
   "checksum": "5422a4136f4efbe4399ae2cbdd20396de9dd4ca52f0de2a13e24b87d6c2fe8da",
   "metal_species": [
      "Si"
   ],
   "non_metal_species": [
      "O"
   ],
   "name": "DFT",
   "uc_volume": 451.65190437499996,
   "density": 1.76724289609504,
   "date_created": "2022-03-08T13:13:06.093527"
}